<meta>
	<info name="Base gamemode"/>
	<min_mta_version server="1.3.3" client="1.3.3"/>

	<!-- Shared -->
	<script src="shared/classlib.lua" type="shared"/>
	<script src="shared/classes/Object.lua" type="shared"/>
	<script src="shared/classes/Singleton.lua" type="shared"/>
	<script src="shared/utils.lua" type="shared"/>
	
	<!-- Server -->
	<script src="server/classes/Storage/SQL.lua" type="server"/>
	<script src="server/classes/Storage/SQLite.lua" type="server"/>
	<script src="server/classes/Storage/MySQL.lua" type="server"/>
	<script src="server/classes/Core.lua" type="server"/>
	<script src="server/classes/MTAElement.lua" type="server"/>
	<script src="server/classes/Player.lua" type="server"/>
	<script src="server/classes/Root.lua" type="server"/>
	
	<script src="shared/utils.lua" type="server"/>
	<script src="server/Main.lua" type="server"/>
	
	<!-- Client -->
	<script src="client/classes/Core.lua" type="client"/>
	<script src="client/classes/MTAElement.lua" type="client"/>
	<script src="client/classes/Player.lua" type="client"/>
	<script src="client/classes/LocalPlayer.lua" type="client"/>
	
	<script src="client/tempLogin.lua" type="client"/>
	<script src="client/Main.lua" type="client"/>
	
	<!-- Files -->
	
</meta>
