<?xml version="1.0" encoding="utf-8"?>
<data xmlns="http://www.woltlab.com" xmlns:xsi="http://www.w3.org/2001/XMLSchema-instance" xsi:schemaLocation="http://www.woltlab.com http://www.woltlab.com/XSD/maelstrom/eventListener.xsd">
    <import>
        <eventlistener>
			<eventclassname>wcf\data\user\UserAction</eventclassname>
			<eventname>initializeAction</eventname>
			<inherit>1</inherit>
			<environment>admin</environment>
			<listenerclassname>wcf\system\event\listener\TeamspeakSyncMainListener</listenerclassname>
		</eventlistener>
        <eventlistener>
			<eventclassname>wcf\data\user\UserAction</eventclassname>
			<eventname>initializeAction</eventname>
			<inherit>1</inherit>
			<environment>user</environment>
			<listenerclassname>wcf\system\event\listener\TeamspeakSyncMainListener</listenerclassname>
		</eventlistener>
		
        <eventlistener>
			<eventclassname>wcf\data\user\UserAction</eventclassname>
			<eventname>finalizeAction</eventname>
			<inherit>1</inherit>
			<environment>admin</environment>
			<listenerclassname>wcf\system\event\listener\TeamspeakSyncMainListener</listenerclassname>
		</eventlistener>
        <eventlistener>
			<eventclassname>wcf\data\user\UserAction</eventclassname>
			<eventname>finalizeAction</eventname>
			<inherit>1</inherit>
			<environment>user</environment>
			<listenerclassname>wcf\system\event\listener\TeamspeakSyncMainListener</listenerclassname>
		</eventlistener>
    </import>
</data>